tox_asdf/__init__.py
tox_asdf/plugin.py
tox_asdf-0.1.0.dist-info/LICENSE
tox_asdf-0.1.0.dist-info/METADATA
tox_asdf-0.1.0.dist-info/WHEEL
tox_asdf-0.1.0.dist-info/entry_points.txt
tox_asdf-0.1.0.dist-info/top_level.txt
tox_asdf-0.1.0.dist-info/RECORD
