Metadata-Version: 2.1
Name: tox-asdf
Version: 0.1.0
Summary: A plugin telling tox to use asdf to find python executables
Home-page: https://github.com/apihackers/tox-asdf
Author: API Hackers
Author-email: pypi+tox-asdf@apihackers.com
License: MIT
Keywords: tox asdf
Platform: UNKNOWN
Classifier: Development Status :: 3 - Alpha
Classifier: Intended Audience :: Developers
Classifier: License :: OSI Approved :: MIT License
Classifier: Operating System :: OS Independent
Classifier: Programming Language :: Python :: 2
Classifier: Programming Language :: Python :: 2.7
Classifier: Programming Language :: Python :: 3
Classifier: Programming Language :: Python :: 3.4
Classifier: Programming Language :: Python :: 3.5
Classifier: Programming Language :: Python :: 3.6
Classifier: Programming Language :: Python :: 3.7
Classifier: Programming Language :: Python :: Implementation :: CPython
Classifier: Programming Language :: Python :: Implementation :: PyPy
Classifier: Programming Language :: Python
Classifier: Topic :: Software Development :: Libraries :: Python Modules
Classifier: Topic :: Software Development
Requires-Dist: tox (>=2.0)
Provides-Extra: test
Requires-Dist: mock (>=2.0.0) ; extra == 'test'
Requires-Dist: pytest (>=4.0.0) ; extra == 'test'
Requires-Dist: pytest-cov ; extra == 'test'
Requires-Dist: pytest-mock ; extra == 'test'
Requires-Dist: pytest-sugar ; extra == 'test'
Requires-Dist: flake8 ; extra == 'test'
Requires-Dist: wheel ; extra == 'test'
Requires-Dist: pluggy (>=0.7) ; extra == 'test'
